template_python_package/__init__.py
template_python_package/main.py
template_python_package-0.1.1.dist-info/LICENSE
template_python_package-0.1.1.dist-info/METADATA
template_python_package-0.1.1.dist-info/WHEEL
template_python_package-0.1.1.dist-info/top_level.txt
template_python_package-0.1.1.dist-info/RECORD
