Metadata-Version: 2.1
Name: template-python-package
Version: 0.1.1
Summary: A template python package for testing pypi releases with azure pipelines
Home-page: https://github.com/umesh-timalsina/template-python-package
Author: Umesh Timalsina
Author-email: umesh.timalsina@vanderbilt.edu
License: MIT
Platform: UNKNOWN
Requires-Python: >=3.6, <4
